linuxrecycle/AutoRegularTask.py
linuxrecycle/DB.py
linuxrecycle/__init__.py
linuxrecycle/argv.py
linuxrecycle/auto_clear.py
linuxrecycle/config.py
linuxrecycle/main.py
linuxrecycle/oper.py
linuxrecycle/printDB.py
linuxrecycle/recover.py
linuxrecycle/setCrontab.py
linuxrecycle/trashInfo.py
linuxrecycle-2.0.6.data/data/LICENSE
linuxrecycle-2.0.6.dist-info/licenses/LICENSE
linuxrecycle-2.0.6.dist-info/METADATA
linuxrecycle-2.0.6.dist-info/WHEEL
linuxrecycle-2.0.6.dist-info/entry_points.txt
linuxrecycle-2.0.6.dist-info/top_level.txt
linuxrecycle-2.0.6.dist-info/RECORD
