Metadata-Version: 2.4
Name: LinuxRecycle
Version: 2.0.6
Summary: A recycle system for linux
Author: Xin-Xin Ma
License: GPL
Project-URL: Source, https://github.com/xxmawhu/LinuxRecycle
License-File: LICENSE
Requires-Dist: termcolor
Dynamic: author
Dynamic: description
Dynamic: license
Dynamic: license-file
Dynamic: project-url
Dynamic: requires-dist
Dynamic: summary
